setup.cfg
setup.py
tdb/__init__.py
tdb/app.py
tdb/debug_session.py
tdb/ht_op.py
tdb/interface.py
tdb/op_store.py
tdb/plot_op.py
tdb/python_op.py
tdb/transitive_closure.py
tdb/examples/__init__.py
tdb/examples/mnist.py
tdb/examples/viz.py
tdb/tests/__init__.py
tdb/tests/run_tests.py
tdb/tests/test_exe_order.py
tdb/tests/test_mixed.py
tdb/tests/test_mnist.py
tdb/tests/test_pure_ht.py
tdb/tests/test_pure_tf.py
tdb/tests/test_ui.py
tfdebugger.egg-info/PKG-INFO
tfdebugger.egg-info/SOURCES.txt
tfdebugger.egg-info/dependency_links.txt
tfdebugger.egg-info/requires.txt
tfdebugger.egg-info/top_level.txt