Metadata-Version: 1.1
Name: tfdebugger
Version: 0.1.1
Summary: TensorFlow Debugger
Home-page: https://github.com/ericjang/tdb
Author: Eric Jang
Author-email: ericjang2004@gmail.com
License: Apache 2.0
Download-URL: https://github.com/ericjang/tdb/archive/0.1.tar.gz
Keywords: TDB,Deep Learning,TensorFlow,debugging,visualization
Platform: UNKNOWN
Classifier: Intended Audience :: Developers
Classifier: Intended Audience :: Science/Research
Classifier: Programming Language :: Python
